kubeflow/optimizer/LICENSE
kubeflow/optimizer/README.md
kubeflow/optimizer/__init__.py
kubeflow/optimizer/api_client.py
kubeflow/optimizer/configuration.py
kubeflow/optimizer/exceptions.py
kubeflow/optimizer/katib_api_pb2.py
kubeflow/optimizer/katib_api_pb2_grpc.py
kubeflow/optimizer/main.py
kubeflow/optimizer/pyproject.toml
kubeflow/optimizer/rest.py
kubeflow/optimizer/api/__init__.py
kubeflow/optimizer/api/katib_client.py
kubeflow/optimizer/api/katib_client_test.py
kubeflow/optimizer/api/report_metrics.py
kubeflow/optimizer/api/report_metrics_test.py
kubeflow/optimizer/api/search.py
kubeflow/optimizer/constants/__init__.py
kubeflow/optimizer/constants/constants.py
kubeflow/optimizer/models/__init__.py
kubeflow/optimizer/models/v1beta1_algorithm_setting.py
kubeflow/optimizer/models/v1beta1_algorithm_spec.py
kubeflow/optimizer/models/v1beta1_collector_spec.py
kubeflow/optimizer/models/v1beta1_config_map_source.py
kubeflow/optimizer/models/v1beta1_early_stopping_rule.py
kubeflow/optimizer/models/v1beta1_early_stopping_setting.py
kubeflow/optimizer/models/v1beta1_early_stopping_spec.py
kubeflow/optimizer/models/v1beta1_experiment.py
kubeflow/optimizer/models/v1beta1_experiment_condition.py
kubeflow/optimizer/models/v1beta1_experiment_list.py
kubeflow/optimizer/models/v1beta1_experiment_spec.py
kubeflow/optimizer/models/v1beta1_experiment_status.py
kubeflow/optimizer/models/v1beta1_feasible_space.py
kubeflow/optimizer/models/v1beta1_file_system_path.py
kubeflow/optimizer/models/v1beta1_filter_spec.py
kubeflow/optimizer/models/v1beta1_graph_config.py
kubeflow/optimizer/models/v1beta1_metric.py
kubeflow/optimizer/models/v1beta1_metric_strategy.py
kubeflow/optimizer/models/v1beta1_metrics_collector_spec.py
kubeflow/optimizer/models/v1beta1_nas_config.py
kubeflow/optimizer/models/v1beta1_objective_spec.py
kubeflow/optimizer/models/v1beta1_observation.py
kubeflow/optimizer/models/v1beta1_operation.py
kubeflow/optimizer/models/v1beta1_optimal_trial.py
kubeflow_sdk-0.1.9.dist-info/METADATA
kubeflow_sdk-0.1.9.dist-info/WHEEL
kubeflow_sdk-0.1.9.dist-info/licenses/LICENSE
kubeflow_sdk-0.1.9.dist-info/RECORD
